docstore_manager/__init__.py
docstore_manager/cli.py
docstore_manager/core/__init__.py
docstore_manager/core/client.py
docstore_manager/core/client_interface.py
docstore_manager/core/command.py
docstore_manager/core/command_interface.py
docstore_manager/core/utils.py
docstore_manager/core/cli/base.py
docstore_manager/core/client/__init__.py
docstore_manager/core/client/base.py
docstore_manager/core/command/__init__.py
docstore_manager/core/command/base.py
docstore_manager/core/config/__init__.py
docstore_manager/core/config/base.py
docstore_manager/core/exceptions/__init__.py
docstore_manager/core/format/__init__.py
docstore_manager/core/format/base.py
docstore_manager/core/format/base_formatter.py
docstore_manager/core/format/formatter_interface.py
docstore_manager/core/logging/__init__.py
docstore_manager/core/response/__init__.py
docstore_manager/qdrant/__init__.py
docstore_manager/qdrant/cli.py
docstore_manager/qdrant/client.py
docstore_manager/qdrant/command.py
docstore_manager/qdrant/commands.py
docstore_manager/qdrant/config.py
docstore_manager/qdrant/format.py
docstore_manager/qdrant/utils.py
docstore_manager/qdrant/commands/__init__.py
docstore_manager/qdrant/commands/batch.py
docstore_manager/qdrant/commands/config.py
docstore_manager/qdrant/commands/count.py
docstore_manager/qdrant/commands/create.py
docstore_manager/qdrant/commands/delete.py
docstore_manager/qdrant/commands/get.py
docstore_manager/qdrant/commands/info.py
docstore_manager/qdrant/commands/list.py
docstore_manager/qdrant/commands/scroll.py
docstore_manager/qdrant/commands/search.py
docstore_manager/solr/__init__.py
docstore_manager/solr/cli.py
docstore_manager/solr/client.py
docstore_manager/solr/command.py
docstore_manager/solr/config.py
docstore_manager/solr/format.py
docstore_manager/solr/utils.py
docstore_manager/solr/commands/__init__.py
docstore_manager/solr/commands/add_documents.py
docstore_manager/solr/commands/config.py
docstore_manager/solr/commands/create.py
docstore_manager-0.1.2.dist-info/licenses/LICENSE
docstore_manager-0.1.2.dist-info/METADATA
docstore_manager-0.1.2.dist-info/WHEEL
docstore_manager-0.1.2.dist-info/entry_points.txt
docstore_manager-0.1.2.dist-info/top_level.txt
docstore_manager-0.1.2.dist-info/RECORD
