Metadata-Version: 2.4
Name: docstore-manager
Version: 0.1.2
Summary: Command-line tools for managing document stores like Qdrant and Solr
Home-page: https://github.com/allenday/docstore-manager
Author: Allen Day
Author-email: Allen Day <allenday@example.com>
License: Apache-2.0
Project-URL: Homepage, https://github.com/allenday/docstore-manager
Project-URL: Bug Reports, https://github.com/allenday/docstore-manager/issues
Classifier: Development Status :: 4 - Beta
Classifier: Intended Audience :: Developers
Classifier: License :: OSI Approved :: Apache Software License
Classifier: Programming Language :: Python :: 3
Classifier: Programming Language :: Python :: 3.8
Classifier: Programming Language :: Python :: 3.9
Classifier: Programming Language :: Python :: 3.10
Requires-Python: >=3.8
License-File: LICENSE
Requires-Dist: qdrant-client>=1.14.2
Requires-Dist: tqdm>=4.66.0
Requires-Dist: pyyaml>=6.0
Requires-Dist: appdirs>=1.4.4
Requires-Dist: pysolr>=3.9.0
Requires-Dist: rich>=13.0.0
Requires-Dist: click>=8.0.0
Requires-Dist: kazoo>=2.9.0
Provides-Extra: dev
Requires-Dist: pytest>=6.0.0; extra == "dev"
Requires-Dist: pytest-cov>=6.0.0; extra == "dev"
Requires-Dist: pytest-mock>=3.14.0; extra == "dev"
Requires-Dist: flake8>=7.0.0; extra == "dev"
Requires-Dist: pylint>=3.0.0; extra == "dev"
Requires-Dist: black>=23.0.0; extra == "dev"
Requires-Dist: isort>=5.12.0; extra == "dev"
Requires-Dist: pre-commit>=3.0.0; extra == "dev"
Requires-Dist: mkdocs>=1.6.0; extra == "dev"
Requires-Dist: mkdocs-material>=9.6.0; extra == "dev"
Requires-Dist: mkdocstrings[python]>=0.29.0; extra == "dev"
Requires-Dist: mkdocs-minify-plugin>=0.8.0; extra == "dev"
Requires-Dist: mkdocs-git-revision-date-localized-plugin>=1.4.0; extra == "dev"
Requires-Dist: mkdocs-macros-plugin>=1.3.0; extra == "dev"
Dynamic: author
Dynamic: home-page
Dynamic: license-file
Dynamic: requires-python
